dever/__init__.py
dever/core.py
dever-0.0.1.dist-info/DESCRIPTION.rst
dever-0.0.1.dist-info/METADATA
dever-0.0.1.dist-info/RECORD
dever-0.0.1.dist-info/WHEEL
dever-0.0.1.dist-info/entry_points.txt
dever-0.0.1.dist-info/metadata.json
dever-0.0.1.dist-info/top_level.txt
